gdnb/__init__.py
gdnb/dataset.py
gdnb/ising_sim.py
gdnb/model.py
gdnb/utils.py
gdnb-0.0.1.dist-info/LICENSE.txt
gdnb-0.0.1.dist-info/METADATA
gdnb-0.0.1.dist-info/WHEEL
gdnb-0.0.1.dist-info/top_level.txt
gdnb-0.0.1.dist-info/RECORD
