Metadata-Version: 2.1
Name: gdnb
Version: 0.0.1
Summary: Implement the GDNB algorithm
Home-page: https://github.com/PengTao-HUST/GDNB
Author: Peng Tao
Author-email: taopeng543@gmail.com
License: MIT Licence
Platform: UNKNOWN
Classifier: Programming Language :: Python :: 3
Requires-Python: >=3.6
Requires-Dist: tqdm
Requires-Dist: seaborn
Requires-Dist: matplotlib
Requires-Dist: numpy
Requires-Dist: scipy
